{"data": {"request": [{"query": "London, United Kingdom", "type": "City"}], "weather": [{"date": "2015-09-12", "maxtempF": "67", "hourly": [{"weatherIconUrl": [{"value": "http://cdn.worldweatheronline.net/images/wsymbols01_png_64/wsymbol_0017_cloudy_with_light_rain.png"}], "cloudcover": "63", "tempC": "20", "winddir16Point": "SW", "humidity": "69", "tempF": "67", "precipMM": "1.0", "WindGustMiles": "18", "windspeedKmph": "20", "WindChillF": "62", "winddirDegree": "232", "HeatIndexF": "62", "DewPointC": "11", "FeelsLikeF": "62", "weatherDesc": [{"value": "Light drizzle"}], "visibility": "9", "WindChillC": "16", "windspeedMiles": "13", "WindGustKmph": "29", "DewPointF": "51", "HeatIndexC": "17", "time": "24", "weatherCode": "266", "pressure": "1009", "FeelsLikeC": "16"}], "maxtempC": "20", "mintempC": "16", "astronomy": [{"sunset": "07:23 PM", "moonrise": "05:36 AM", "moonset": "06:57 PM", "sunrise": "06:30 AM"}], "mintempF": "60", "uvIndex": "0"}]}}