{"data": {"request": [{"query": "West Bromwich, United Kingdom", "type": "City"}], "weather": [{"date": "2015-10-17", "maxtempF": "54", "hourly": [{"weatherIconUrl": [{"value": "http://cdn.worldweatheronline.net/images/wsymbols01_png_64/wsymbol_0009_light_rain_showers.png"}], "cloudcover": "69", "tempC": "12", "winddir16Point": "NNE", "humidity": "84", "tempF": "54", "precipMM": "0.1", "WindGustMiles": "18", "windspeedKmph": "15", "WindChillF": "42", "winddirDegree": "24", "HeatIndexF": "47", "DewPointC": "6", "FeelsLikeF": "42", "weatherDesc": [{"value": "Patchy rain possible"}], "visibility": "10", "WindChillC": "5", "windspeedMiles": "10", "WindGustKmph": "29", "DewPointF": "42", "HeatIndexC": "8", "time": "24", "weatherCode": "176", "pressure": "1022", "FeelsLikeC": "5"}], "maxtempC": "12", "mintempC": "5", "astronomy": [{"sunset": "06:09 PM", "moonrise": "11:53 AM", "moonset": "08:53 PM", "sunrise": "07:37 AM"}], "mintempF": "41", "uvIndex": "0"}]}}