{"data": {"request": [{"query": "Manchester, United Kingdom", "type": "City"}], "weather": [{"uvIndex": "0", "date": "2015-11-21", "astronomy": [{"sunrise": "08:45 AM", "sunset": "05:04 PM", "moonrise": "03:08 PM", "moonset": "02:23 AM"}], "maxtempC": "3", "mintempF": "33", "maxtempF": "38", "hourly": [{"windspeedMiles": "17", "WindChillF": "26", "FeelsLikeF": "26", "visibility": "9", "windspeedKmph": "28", "winddirDegree": "328", "time": "24", "WindGustKmph": "43", "WindGustMiles": "27", "weatherCode": "116", "precipMM": "1.4", "HeatIndexC": "2", "tempC": "3", "weatherIconUrl": [{"value": "http://cdn.worldweatheronline.net/images/wsymbols01_png_64/wsymbol_0002_sunny_intervals.png"}], "humidity": "73", "weatherDesc": [{"value": "Partly cloudy"}], "WindChillC": "-3", "tempF": "38", "DewPointF": "27", "pressure": "1011", "HeatIndexF": "35", "DewPointC": "-3", "winddir16Point": "NNW", "cloudcover": "35", "FeelsLikeC": "-3"}], "mintempC": "1"}]}}